cli/__init__.py
cli/batch.py
cli/download_examples.py
cli/grade.py
cli/randex.py
cli/random_answers.py
cli/validate.py
randex/__init__.py
randex/cli.py
randex/exam.py
randex-0.4.3.dist-info/LICENSE
randex-0.4.3.dist-info/METADATA
randex-0.4.3.dist-info/WHEEL
randex-0.4.3.dist-info/entry_points.txt
randex-0.4.3.dist-info/RECORD
