Metadata-Version: 2.3
Name: randex
Version: 0.4.3
Summary: Create randomized multiple choice exams using latex.
License: CC BY-NC 4.0
Author: G. Arampatzis
Author-email: gtarabat@gmail.com
Requires-Python: >=3.10,<4.0
Classifier: License :: Other/Proprietary License
Classifier: Operating System :: OS Independent
Classifier: Programming Language :: Python :: 3
Classifier: Programming Language :: Python :: 3.10
Classifier: Programming Language :: Python :: 3.11
Classifier: Programming Language :: Python :: 3.12
Classifier: Programming Language :: Python :: 3.13
Requires-Dist: cerberus (>=1.3.5,<2.0.0)
Requires-Dist: click (>=8.1.7,<9.0.0)
Requires-Dist: pp-ez (>=0.2.0,<0.3.0)
Requires-Dist: pprintpp (>=0.4.0,<0.5.0)
Requires-Dist: pretty-errors (>=1.2.25,<2.0.0)
Requires-Dist: pydantic (>=2.11.7,<3.0.0)
Requires-Dist: pypdf (>=4.2.0,<5.0.0)
Requires-Dist: pyyaml (>=6.0.1,<7.0.0)
Requires-Dist: tqdm (>=4.67.1,<5.0.0)
Requires-Dist: typing-extensions (>=4.12.0,<5.0.0)
Project-URL: Homepage, https://github.com/arampatzis/randex
